gmaps_avoid_swiss/__init__.py
gmaps_avoid_swiss/client.py
gmaps_avoid_swiss/geo_check.py
gmaps_avoid_swiss/routes.py
gmaps_avoid_swiss/waypoints.py
gmaps_avoid_swiss/data/switzerland.geojson
gmaps_avoid_swiss-0.1.11.dist-info/AUTHORS.rst
gmaps_avoid_swiss-0.1.11.dist-info/LICENSE
gmaps_avoid_swiss-0.1.11.dist-info/METADATA
gmaps_avoid_swiss-0.1.11.dist-info/WHEEL
gmaps_avoid_swiss-0.1.11.dist-info/top_level.txt
gmaps_avoid_swiss-0.1.11.dist-info/RECORD
