Metadata-Version: 2.1
Name: gmaps-avoid-swiss
Version: 0.1.11
Summary: A Python package that customizes Google Maps routing to avoid Swiss routes unless the origin, destination, or waypoints include locations within Switzerland.
Home-page: https://github.com/xbencat/gmaps_avoid_swiss
Author: Gregor Bencat
Author-email: Gregor Bencat <bencat.gregor@gmail.com>
Maintainer-email: Gregor Bencat <bencat.gregor@gmail.com>
License: MIT license
Project-URL: bugs, https://github.com/xbencat/gmaps_avoid_swiss/issues
Project-URL: changelog, https://github.com/xbencat/gmaps_avoid_swiss/blob/master/changelog.md
Project-URL: homepage, https://github.com/xbencat/gmaps_avoid_swiss
License-File: LICENSE
License-File: AUTHORS.rst
Requires-Dist: google-maps-routing
Requires-Dist: numpy
Requires-Dist: shapely
Requires-Dist: polyline
Provides-Extra: dev
Requires-Dist: coverage ; extra == 'dev'
Requires-Dist: mypy ; extra == 'dev'
Requires-Dist: pytest ; extra == 'dev'
Requires-Dist: ruff ; extra == 'dev'
